<?xml version="1.0"?>
<taskDescriptor xmlns="http://been.d3s.mff.cuni.cz/taskmanager/td"
				groupId="cz.cuni.mff.d3s.been.jackson" bpkId="serialize" version="0.0.1-SNAPSHOT"
				name="jackson-serialize">
	<hostRuntimes />
	<taskProperties>
		<taskProperty key="dataType" value="ARRAY" />
		
		<taskProperty key="cachePolicy" value="OM_CACHE" />
		
		<taskProperty key="repetitions" value="10000" />
	</taskProperties>
	
	<!-- 
	<debug>
		<mode>connect</mode>
		<host>localhost</host>
		<port>12345</port>
		<suspend>false</suspend>
	</debug>
	 -->
</taskDescriptor>
